schemate/__init__.py
schemate/__main__.py
schemate/analyze.py
schemate/config.py
schemate/exceptions.py
schemate/loaders.py
schemate/schemate.py
schemate/serialize.py
schemate/types.py
schemate/version.py
schemate-0.2.0.dist-info/licenses/LICENSE
schemate-0.2.0.dist-info/METADATA
schemate-0.2.0.dist-info/WHEEL
schemate-0.2.0.dist-info/entry_points.txt
schemate-0.2.0.dist-info/top_level.txt
schemate-0.2.0.dist-info/zip-safe
schemate-0.2.0.dist-info/RECORD
