Metadata-Version: 2.4
Name: schemate
Version: 0.2.0
Summary: Analyzes NoSQL or JSON documents to try to infer a schema or general properties.
Download-URL: https://github.com/rotationalio/llm-benchmark/tarball/v0.2.0
Author: Rotational Labs
Author-email: support@rotational.io
Maintainer: Rotational Labs
Maintainer-email: support@rotational.io
License: BSD 3
Project-URL: Download, https://github.com/rotationalio/llm-benchmark/tarball/v0.2.0
Project-URL: Source, https://github.com/rotationalio/llm-benchmark
Project-URL: Tracker, https://github.com/rotationalio/llm-benchmark/issues
Keywords: json,nosql,schema
Classifier: Development Status :: 3 - Alpha
Classifier: Intended Audience :: Developers
Classifier: Intended Audience :: System Administrators
Classifier: License :: OSI Approved :: BSD License
Classifier: Natural Language :: English
Classifier: Operating System :: OS Independent
Classifier: Programming Language :: Python
Classifier: Programming Language :: Python :: 3.12
Classifier: Topic :: System :: Benchmark
Classifier: Topic :: System :: Hardware
Requires-Python: >=3.10, <4
License-File: LICENSE
Requires-Dist: colorama==0.4.6
Requires-Dist: pymongo==4.11.3
Requires-Dist: PyYAML==6.0.2
Dynamic: author
Dynamic: author-email
Dynamic: classifier
Dynamic: description
Dynamic: description-content-type
Dynamic: download-url
Dynamic: keywords
Dynamic: license
Dynamic: license-file
Dynamic: maintainer
Dynamic: maintainer-email
Dynamic: project-url
Dynamic: requires-dist
Dynamic: requires-python
Dynamic: summary
